{"player_id": "3306", "name": "Jordan Howard", "position": "RB", "nfl_team": "", "current_bmfffl_owner": null, "ownership_history": [{"player_id": "3306", "player_name": "Jordan Howard", "position": "RB", "owner": "JuicyBussy", "acquisition_type": "auction_draft", "acquisition_season": "2016", "acquisition_date": 1472688000000, "acquisition_cost": 1, "acquisition_pick": null, "release_type": "dropped", "release_date": 1504224000000, "release_season": "2017", "data_source": "espn_auction_drafts", "notes": null, "dynasty_adp_at_acquisition": {"rank": 17, "pos_rank": "RB5", "adp": 17, "year": 2017, "percentile": 94, "total_ranked": 272}}, {"player_id": "3306", "player_name": "Jordan Howard", "position": "RB", "owner": "rbr", "acquisition_type": "waiver", "acquisition_season": "2021", "acquisition_date": 1635882372723, "acquisition_cost": 469, "acquisition_pick": null, "release_type": "dropped", "release_date": 1662500716984, "release_season": "2022", "data_source": "league_transactions", "notes": null, "dynasty_adp_at_acquisition": {"rank": 328, "pos_rank": "RB99", "adp": 264, "year": 2021, "percentile": 17, "total_ranked": 396}}], "weekly_performance": [{"year": 2020, "week": 1, "pts": 6.7, "started": false, "roster_id": 8, "owner": "JuicyBussy"}, {"year": 2020, "week": 2, "pts": 6.4, "started": false, "roster_id": 8, "owner": "JuicyBussy"}, {"year": 2020, "week": 3, "pts": 6.1, "started": false, "roster_id": 8, "owner": "JuicyBussy"}, {"year": 2020, "week": 4, "pts": -0.6, "started": false, "roster_id": 8, "owner": "JuicyBussy"}, {"year": 2020, "week": 5, "pts": 0, "started": false, "roster_id": 8, "owner": "JuicyBussy"}, {"year": 2020, "week": 6, "pts": 0, "started": false, "roster_id": 8, "owner": "JuicyBussy"}, {"year": 2020, "week": 7, "pts": 0, "started": false, "roster_id": 8, "owner": "JuicyBussy"}, {"year": 2020, "week": 8, "pts": 0, "started": false, "roster_id": 8, "owner": "JuicyBussy"}, {"year": 2020, "week": 9, "pts": 7.9, "started": true, "roster_id": 8, "owner": "JuicyBussy"}, {"year": 2020, "week": 10, "pts": 0, "started": false, "roster_id": 8, "owner": "JuicyBussy"}, {"year": 2020, "week": 11, "pts": 0, "started": false, "roster_id": 8, "owner": "JuicyBussy"}, {"year": 2020, "week": 12, "pts": 0, "started": false, "roster_id": 8, "owner": "JuicyBussy"}, {"year": 2020, "week": 13, "pts": 1.9, "started": false, "roster_id": 8, "owner": "JuicyBussy"}, {"year": 2020, "week": 14, "pts": 0, "started": false, "roster_id": 8, "owner": "JuicyBussy"}, {"year": 2020, "week": 15, "pts": 0, "started": false, "roster_id": 8, "owner": "JuicyBussy"}, {"year": 2020, "week": 16, "pts": 0.8, "started": false, "roster_id": 8, "owner": "JuicyBussy"}, {"year": 2020, "week": 17, "pts": 0, "started": false, "roster_id": 8, "owner": "JuicyBussy"}, {"year": 2021, "week": 9, "pts": 13.1, "started": false, "roster_id": 3, "owner": "rbr"}, {"year": 2021, "week": 10, "pts": 8.3, "started": true, "roster_id": 3, "owner": "rbr"}, {"year": 2021, "week": 11, "pts": 6.3, "started": false, "roster_id": 3, "owner": "rbr"}, {"year": 2021, "week": 12, "pts": 0, "started": false, "roster_id": 3, "owner": "rbr"}, {"year": 2021, "week": 13, "pts": 0, "started": false, "roster_id": 3, "owner": "rbr"}, {"year": 2021, "week": 14, "pts": 0, "started": false, "roster_id": 3, "owner": "rbr"}, {"year": 2021, "week": 15, "pts": 6.9, "started": false, "roster_id": 3, "owner": "rbr"}, {"year": 2021, "week": 16, "pts": 6.6, "started": true, "roster_id": 3, "owner": "rbr"}, {"year": 2021, "week": 17, "pts": 2.6, "started": false, "roster_id": 3, "owner": "rbr"}, {"year": 2021, "week": 18, "pts": 0, "started": false, "roster_id": 3, "owner": "rbr"}], "dynasty_adp_history": {"2017": {"rank": 17, "pos_rank": "RB5", "adp": 17.0}, "2018": {"rank": 27, "pos_rank": "RB14", "adp": 28.0}, "2019": {"rank": 97, "pos_rank": "RB37", "adp": 100.5}, "2020": {"rank": 138, "pos_rank": "RB43", "adp": 139.0}, "2021": {"rank": 328, "pos_rank": "RB99", "adp": 264.0}}, "career_bmfffl": {"total_pts_started": 22.8, "total_pts_benched": 50.2, "weeks_started": 3, "weeks_benched": 24, "avg_pts_started": 7.6, "avg_pts_benched": 2.09}, "ktc": null}