{"player_id": "4179", "name": "Joshua Dobbs", "position": "QB", "nfl_team": "", "current_bmfffl_owner": null, "ownership_history": [{"player_id": "4179", "player_name": "Joshua Dobbs", "position": "QB", "owner": "Grandes", "acquisition_type": "waiver", "acquisition_season": "2018", "acquisition_date": 1540520261349, "acquisition_cost": null, "acquisition_pick": null, "release_type": "dropped", "release_date": 1663501956374, "release_season": "2022", "data_source": "espn_mroster_2018", "notes": null, "dynasty_adp_at_acquisition": null}, {"player_id": "4179", "player_name": "Joshua Dobbs", "position": "QB", "owner": "eldridsm", "acquisition_type": "waiver", "acquisition_season": "2022", "acquisition_date": 1663501956374, "acquisition_cost": 0, "acquisition_pick": null, "release_type": "dropped", "release_date": 1663762682229, "release_season": "2022", "data_source": "league_transactions", "notes": null, "dynasty_adp_at_acquisition": null}, {"player_id": "4179", "player_name": "Joshua Dobbs", "position": "QB", "owner": "MLSchools12", "acquisition_type": "waiver", "acquisition_season": "2023", "acquisition_date": 1693077695528, "acquisition_cost": 27, "acquisition_pick": null, "release_type": "dropped", "release_date": 1693160131207, "release_season": "2023", "data_source": "league_transactions", "notes": null, "dynasty_adp_at_acquisition": null}, {"player_id": "4179", "player_name": "Joshua Dobbs", "position": "QB", "owner": "MLSchools12", "acquisition_type": "waiver", "acquisition_season": "2023", "acquisition_date": 1693258363516, "acquisition_cost": 69, "acquisition_pick": null, "release_type": "dropped", "release_date": 1731632008146, "release_season": "2024", "data_source": "league_transactions", "notes": null, "dynasty_adp_at_acquisition": null}, {"player_id": "4179", "player_name": "Joshua Dobbs", "position": "QB", "owner": "SexMachineAndyD", "acquisition_type": "waiver", "acquisition_season": "2024", "acquisition_date": 1732340990538, "acquisition_cost": 7, "acquisition_pick": null, "release_type": "dropped", "release_date": 1732687711753, "release_season": "2024", "data_source": "league_transactions", "notes": null, "dynasty_adp_at_acquisition": null}], "weekly_performance": [{"year": 2022, "week": 2, "pts": 0, "started": false, "roster_id": 10, "owner": "eldridsm"}, {"year": 2023, "week": 1, "pts": 0.98, "started": false, "roster_id": 5, "owner": "MLSchools12"}, {"year": 2023, "week": 2, "pts": 25.22, "started": false, "roster_id": 5, "owner": "MLSchools12"}, {"year": 2023, "week": 3, "pts": 17.06, "started": false, "roster_id": 5, "owner": "MLSchools12"}, {"year": 2023, "week": 4, "pts": 23.4, "started": false, "roster_id": 5, "owner": "MLSchools12"}, {"year": 2023, "week": 5, "pts": 10.74, "started": true, "roster_id": 5, "owner": "MLSchools12"}, {"year": 2023, "week": 6, "pts": 11.1, "started": true, "roster_id": 5, "owner": "MLSchools12"}, {"year": 2023, "week": 7, "pts": 16.14, "started": true, "roster_id": 5, "owner": "MLSchools12"}, {"year": 2023, "week": 8, "pts": 24.92, "started": false, "roster_id": 5, "owner": "MLSchools12"}, {"year": 2023, "week": 9, "pts": 24.92, "started": false, "roster_id": 5, "owner": "MLSchools12"}, {"year": 2023, "week": 10, "pts": 25.12, "started": false, "roster_id": 5, "owner": "MLSchools12"}, {"year": 2023, "week": 11, "pts": 17.94, "started": false, "roster_id": 5, "owner": "MLSchools12"}, {"year": 2023, "week": 12, "pts": 8.5, "started": false, "roster_id": 5, "owner": "MLSchools12"}, {"year": 2023, "week": 13, "pts": 0, "started": false, "roster_id": 5, "owner": "MLSchools12"}, {"year": 2023, "week": 14, "pts": 4.62, "started": true, "roster_id": 5, "owner": "MLSchools12"}, {"year": 2023, "week": 15, "pts": 0, "started": false, "roster_id": 5, "owner": "MLSchools12"}, {"year": 2023, "week": 16, "pts": 0, "started": false, "roster_id": 5, "owner": "MLSchools12"}, {"year": 2023, "week": 17, "pts": 0, "started": false, "roster_id": 5, "owner": "MLSchools12"}, {"year": 2023, "week": 18, "pts": 0, "started": false, "roster_id": 5, "owner": "MLSchools12"}, {"year": 2024, "week": 1, "pts": 0, "started": false, "roster_id": 5, "owner": "MLSchools12"}, {"year": 2024, "week": 2, "pts": 0, "started": false, "roster_id": 5, "owner": "MLSchools12"}, {"year": 2024, "week": 3, "pts": 0, "started": false, "roster_id": 5, "owner": "MLSchools12"}, {"year": 2024, "week": 4, "pts": 0, "started": false, "roster_id": 5, "owner": "MLSchools12"}, {"year": 2024, "week": 5, "pts": 0, "started": false, "roster_id": 5, "owner": "MLSchools12"}, {"year": 2024, "week": 6, "pts": 0, "started": false, "roster_id": 5, "owner": "MLSchools12"}, {"year": 2024, "week": 7, "pts": 0, "started": false, "roster_id": 5, "owner": "MLSchools12"}, {"year": 2024, "week": 8, "pts": 0, "started": false, "roster_id": 5, "owner": "MLSchools12"}, {"year": 2024, "week": 9, "pts": 0, "started": false, "roster_id": 5, "owner": "MLSchools12"}, {"year": 2024, "week": 10, "pts": 0, "started": false, "roster_id": 5, "owner": "MLSchools12"}, {"year": 2024, "week": 12, "pts": 0, "started": false, "roster_id": 2, "owner": "SexMachineAndyD"}], "dynasty_adp_history": {}, "career_bmfffl": {"total_pts_started": 42.6, "total_pts_benched": 168.06, "weeks_started": 4, "weeks_benched": 26, "avg_pts_started": 10.65, "avg_pts_benched": 6.46}, "ktc": null}