{"player_id": "9480", "name": "Brenton Strange", "position": "TE", "nfl_team": "", "current_bmfffl_owner": "eldridm20", "ownership_history": [{"player_id": "9480", "player_name": "Brenton Strange", "position": "TE", "owner": "eldridm20", "acquisition_type": "waiver", "acquisition_season": "2023", "acquisition_date": 1689783332007, "acquisition_cost": 9, "acquisition_pick": null, "release_type": "still_held", "release_date": null, "release_season": null, "data_source": "league_transactions", "notes": null, "dynasty_adp_at_acquisition": {"rank": 279, "pos_rank": "TE38", "adp": 268, "year": 2023, "percentile": 12, "total_ranked": 316}}], "weekly_performance": [{"year": 2023, "week": 1, "pts": 0, "started": false, "roster_id": 7, "owner": "eldridm20"}, {"year": 2023, "week": 2, "pts": 0, "started": false, "roster_id": 7, "owner": "eldridm20"}, {"year": 2023, "week": 3, "pts": 1.7, "started": false, "roster_id": 7, "owner": "eldridm20"}, {"year": 2023, "week": 4, "pts": 0, "started": false, "roster_id": 7, "owner": "eldridm20"}, {"year": 2023, "week": 5, "pts": 0, "started": false, "roster_id": 7, "owner": "eldridm20"}, {"year": 2023, "week": 6, "pts": 9.7, "started": false, "roster_id": 7, "owner": "eldridm20"}, {"year": 2023, "week": 7, "pts": 0, "started": false, "roster_id": 7, "owner": "eldridm20"}, {"year": 2023, "week": 8, "pts": 0, "started": false, "roster_id": 7, "owner": "eldridm20"}, {"year": 2023, "week": 9, "pts": 0, "started": false, "roster_id": 7, "owner": "eldridm20"}, {"year": 2023, "week": 10, "pts": 0, "started": false, "roster_id": 7, "owner": "eldridm20"}, {"year": 2023, "week": 11, "pts": 0, "started": false, "roster_id": 7, "owner": "eldridm20"}, {"year": 2023, "week": 12, "pts": 0, "started": false, "roster_id": 7, "owner": "eldridm20"}, {"year": 2023, "week": 13, "pts": 0, "started": false, "roster_id": 7, "owner": "eldridm20"}, {"year": 2023, "week": 14, "pts": 0, "started": false, "roster_id": 7, "owner": "eldridm20"}, {"year": 2023, "week": 15, "pts": 0, "started": false, "roster_id": 7, "owner": "eldridm20"}, {"year": 2023, "week": 16, "pts": 0, "started": false, "roster_id": 7, "owner": "eldridm20"}, {"year": 2023, "week": 17, "pts": 0.6, "started": false, "roster_id": 7, "owner": "eldridm20"}, {"year": 2023, "week": 18, "pts": 0, "started": false, "roster_id": 7, "owner": "eldridm20"}, {"year": 2024, "week": 1, "pts": 0, "started": false, "roster_id": 7, "owner": "eldridm20"}, {"year": 2024, "week": 2, "pts": 8.0, "started": false, "roster_id": 7, "owner": "eldridm20"}, {"year": 2024, "week": 3, "pts": 8.2, "started": true, "roster_id": 7, "owner": "eldridm20"}, {"year": 2024, "week": 4, "pts": 3.4, "started": false, "roster_id": 7, "owner": "eldridm20"}, {"year": 2024, "week": 5, "pts": 10.4, "started": false, "roster_id": 7, "owner": "eldridm20"}, {"year": 2024, "week": 6, "pts": 1.6, "started": false, "roster_id": 7, "owner": "eldridm20"}, {"year": 2024, "week": 7, "pts": 0, "started": false, "roster_id": 7, "owner": "eldridm20"}, {"year": 2024, "week": 8, "pts": 8.4, "started": false, "roster_id": 7, "owner": "eldridm20"}, {"year": 2024, "week": 9, "pts": 0, "started": false, "roster_id": 7, "owner": "eldridm20"}, {"year": 2024, "week": 10, "pts": 3.5, "started": false, "roster_id": 7, "owner": "eldridm20"}, {"year": 2024, "week": 11, "pts": 1.1, "started": false, "roster_id": 7, "owner": "eldridm20"}, {"year": 2024, "week": 12, "pts": 0, "started": false, "roster_id": 7, "owner": "eldridm20"}, {"year": 2024, "week": 13, "pts": 1.9, "started": false, "roster_id": 7, "owner": "eldridm20"}, {"year": 2024, "week": 14, "pts": 2.6, "started": false, "roster_id": 7, "owner": "eldridm20"}, {"year": 2024, "week": 15, "pts": 12.8, "started": false, "roster_id": 7, "owner": "eldridm20"}, {"year": 2024, "week": 16, "pts": 1.2, "started": true, "roster_id": 7, "owner": "eldridm20"}, {"year": 2024, "week": 17, "pts": 0, "started": true, "roster_id": 7, "owner": "eldridm20"}, {"year": 2024, "week": 18, "pts": 8.0, "started": true, "roster_id": 7, "owner": "eldridm20"}, {"year": 2025, "week": 1, "pts": 7.9, "started": false, "roster_id": 7, "owner": "eldridm20"}, {"year": 2025, "week": 2, "pts": 3.2, "started": true, "roster_id": 7, "owner": "eldridm20"}, {"year": 2025, "week": 3, "pts": 9.1, "started": true, "roster_id": 7, "owner": "eldridm20"}, {"year": 2025, "week": 4, "pts": 7.5, "started": true, "roster_id": 7, "owner": "eldridm20"}, {"year": 2025, "week": 5, "pts": 2.7, "started": true, "roster_id": 7, "owner": "eldridm20"}, {"year": 2025, "week": 6, "pts": 0, "started": false, "roster_id": 7, "owner": "eldridm20"}, {"year": 2025, "week": 7, "pts": 0, "started": false, "roster_id": 7, "owner": "eldridm20"}, {"year": 2025, "week": 8, "pts": 0, "started": false, "roster_id": 7, "owner": "eldridm20"}, {"year": 2025, "week": 9, "pts": 0, "started": false, "roster_id": 7, "owner": "eldridm20"}, {"year": 2025, "week": 10, "pts": 0, "started": false, "roster_id": 7, "owner": "eldridm20"}, {"year": 2025, "week": 11, "pts": 0, "started": false, "roster_id": 7, "owner": "eldridm20"}, {"year": 2025, "week": 12, "pts": 11.8, "started": false, "roster_id": 7, "owner": "eldridm20"}, {"year": 2025, "week": 13, "pts": 12.0, "started": false, "roster_id": 7, "owner": "eldridm20"}, {"year": 2025, "week": 14, "pts": 4.2, "started": false, "roster_id": 7, "owner": "eldridm20"}, {"year": 2025, "week": 15, "pts": 3.1, "started": false, "roster_id": 7, "owner": "eldridm20"}, {"year": 2025, "week": 16, "pts": 12.4, "started": false, "roster_id": 7, "owner": "eldridm20"}, {"year": 2025, "week": 17, "pts": 6.9, "started": false, "roster_id": 7, "owner": "eldridm20"}, {"year": 2025, "week": 18, "pts": 14.2, "started": false, "roster_id": 7, "owner": "eldridm20"}], "dynasty_adp_history": {"2023": {"rank": 279, "pos_rank": "TE38", "adp": 268.0}, "2025": {"rank": 177, "pos_rank": "TE24", "adp": 180.0}, "2026": {"rank": 94, "pos_rank": "TE13", "adp": 94.0}}, "career_bmfffl": {"total_pts_started": 39.9, "total_pts_benched": 138.2, "weeks_started": 8, "weeks_benched": 46, "avg_pts_started": 4.99, "avg_pts_benched": 3.0}, "ktc": {"ktc_value_sf": 3091, "ktc_rank_sf": 147, "ktc_pos_rank_sf": 15, "ktc_value_1qb": 3711, "ktc_rank_1qb": 146, "ktc_player_id": 1461, "ktc_age": 25.3, "ktc_as_of": "2026-05-03"}, "sflex": {"sflex_rank": 216, "sflex_pos_rank": "TE27", "sflex_value": 60, "sflex_as_of": "2026-05-03"}}